[
    {
        "id": 1,
        "title": "SOFA",
        "label": "Design",
        "img": "./img/1.png",
        "active": false
    },
    {
        "id": 2,
        "title": "KeyBoard",
        "label": "Branding",
        "img": "./img/2.png",
        "active": false
    },
    {
        "id": 3,
        "title": "Work Media",
        "label": "Illustration",
        "img": "./img/3.png",
        "active": false
    },
    {
        "id": 4,
        "title": "DDDone",
        "label": "Motion",
        "img": "./img/4.png",
        "active": false
    },
    {
        "id": 5,
        "title": "Abstract",
        "label": "Design",
        "img": "./img/5.png",
        "active": false
    },
    {
        "id": 6,
        "title": "HandP",
        "label": "Branding",
        "img": "./img/6.png",
        "active": false
    },
    {
        "id": 7,
        "title": "Architect",
        "label": "Motion",
        "img": "./img/7.png",
        "active": false
    },
    {
        "id": 8,
        "title": "CalC",
        "label": "Design",
        "img": "./img/8.png",
        "active": false
    },
    {
        "id": 9,
        "title": "Sport",
        "label": "Branding",
        "img": "./img/9.png",
        "active": false
    },
    {
        "id": 10,
        "title": "SOFA2",
        "label": "Design",
        "img": "./img/1.png",
        "active": false
    },
    {
        "id": 11,
        "title": "KeyBoard2",
        "label": "Branding",
        "img": "./img/2.png",
        "active": false
    },
    {
        "id": 12,
        "title": "Work Media2",
        "label": "Illustration",
        "img": "./img/3.png",
        "active": false
    },
    {
        "id": 13,
        "title": "DDDone2",
        "label": "Motion",
        "img": "./img/4.png",
        "active": false
    },
    {
        "id": 14,
        "title": "Abstract2",
        "label": "Design",
        "img": "./img/5.png",
        "active": false
    },
    {
        "id": 15,
        "title": "HandP2",
        "label": "Branding",
        "img": "./img/6.png",
        "active": false
    },
    {
        "id": 16,
        "title": "Architect2",
        "label": "Motion",
        "img": "./img/7.png",
        "active": false
    },
    {
        "id": 17,
        "title": "CalC2",
        "label": "Design",
        "img": "./img/8.png",
        "active": false
    },
    {
        "id": 18,
        "title": "Sport2",
        "label": "Branding",
        "img": "./img/9.png",
        "active": false
    }
]
